Workbook

Sheet Ringkasan
B2: DESCHAIN — MODEL KELAYAKAN BISNIS & PROYEKSI KEUANGAN
B3: PIDI Digdaya X Hackathon 2026 · skenario Konservatif / Basis / Optimis · semua angka = PROYEKSI berbasis asumsi
B6: VONIS KELAYAKAN (skenario Basis)
B7: LTV/CAC | D7: =UnitEconomics!D15 -> 120000
B8: Payback period (bulan) | D8: =UnitEconomics!D16 -> 2.6373626
B9: Break-even operasional (UMKM aktif) | D9: =Proyeksi!C20 -> 2747.2527
B10: Pendapatan Tahun 3 (Rp) | D10: =Proyeksi!E9 -> 23400000000
B11: EBITDA Tahun 3 (Rp) | D11: =Proyeksi!E14 -> 14600000000
B12: SOM 3 tahun (UMKM aktif) | D12: ='TAM-SAM-SOM'!C7 -> 50000
B13: Potensi pendapatan SOM/tahun (Rp) | D13: ='TAM-SAM-SOM'!C10 -> 39000000000
B15: Interpretasi ringkas:
B16: • LTV/CAC > 3 = sehat. Basis ~ (lihat sel) menandakan unit economics kuat; Optimis sangat tinggi, Konservatif tetap layak.
B17: • Payback < 12 bulan = modal akuisisi kembali cepat.
B18: • Break-even operasional tercapai di kisaran ribuan UMKM aktif — realistis dalam ~18–24 bulan.
B19: • Risiko utama: volume transaksi per UMKM (GMV) & retensi belum terbukti; adopsi lending sektor grocery masih rendah (~3%).
B20: • Kesimpulan: MENJANJIKAN pada skenario Basis, DENGAN SYARAT density matching & GMV per user terpenuhi lewat pilot.

Sheet Grafik
B2: GRAFIK PROYEKSI (skenario Basis)
B4: Tahun | C4: Pendapatan (Rp) | D4: EBITDA (Rp)
B5: Tahun 1 | C5: =Proyeksi!C9 -> 429000000 | D5: =Proyeksi!C14 -> -279000000
B6: Tahun 2 | C6: =Proyeksi!D9 -> 4290000000 | D6: =Proyeksi!D14 -> 1710000000
B7: Tahun 3 | C7: =Proyeksi!E9 -> 23400000000 | D7: =Proyeksi!E14 -> 14600000000
B10: Tahun | C10: UMKM aktif (akhir)
B11: Tahun 1 | C11: =Proyeksi!C6 -> 1000
B12: Tahun 2 | C12: =Proyeksi!D6 -> 10000
B13: Tahun 3 | C13: =Proyeksi!E6 -> 50000
B16: Skenario | C16: LTV/CAC (x)
B17: Konservatif | C17: =UnitEconomics!C17 -> 2.4
B18: Basis | C18: =UnitEconomics!D17 -> 10.532407
B19: Optimis | C19: =UnitEconomics!E17 -> 37.5

Sheet UnitEconomics
B2: UNIT ECONOMICS PER UMKM (3 SKENARIO)
B4: Metrik | C4: Konservatif | D4: Basis | E4: Optimis | F4: Catatan / Sumber
B5: GMV / UMKM aktif / bulan (Rp) | C5: 2000000 | D5: 3000000 | E5: 5000000 | F5: Porsi pengadaan lewat platform; warung belanja stok Rp7–21jt/bln (~70% omzet). Sumber: kiosbank.id, ukmindonesia.id
B6: Take rate (fee transaksi) | C6: 0.01 | D6: 0.015 | E6: 0.02 | F6: Take rate B2B Indonesia 1,5–2,0%; range global 0,1–3%. Sumber: BCG, a16z, ASEAN Digital Economy 2025
B7: Fee transaksi / bulan (Rp) | C7: =C5*C6 -> 20000 | D7: =D5*D6 -> 45000 | E7: =E5*E6 -> 100000 | F7: =gmv × take rate -> #N/A
B8: Subscription ARPU / bulan (Rp) | C8: 10000 | D8: 20000 | E8: 40000 | F8: Freemium; blended lintas free+paid (paid Rp99K–999K).
B9: ARPU total / bulan (Rp) | C9: =C7+C8 -> 30000 | D9: =D7+D8 -> 65000 | E9: =E7+E8 -> 140000 | F9: =fee + subscription -> #NAME?
B10: Gross margin | C10: 0.6 | D10: 0.7 | E10: 0.75 | F10: Setelah payment, cloud, support. Software-driven.
B11: Kontribusi / UMKM / bulan (Rp) | C11: =C9*C10 -> 18000 | D11: =D9*D10 -> 45500 | E11: =E9*E10 -> 105000 | F11: =arpu × gross margin -> #N/A
B12: Churn bulanan | C12: 0.05 | D12: 0.036 | E12: 0.028 | F12: Konservatif 5% (umur ~20 bln) → Optimis 2,8% (~36 bln).
B13: Umur pelanggan (bulan) | C13: =1/C12 -> 20 | D13: =1/D12 -> 27.777778 | E13: =1/E12 -> 35.714286 | F13: =1 / churn bulanan -> #VALUE!
B14: LTV (Rp) | C14: =C11*C13 -> 360000 | D14: =D11*D13 -> 1263888.9 | E14: =E11*E13 -> 3750000 | F14: =kontribusi/bln × umur pelanggan -> #N/A
B15: CAC (Rp) | C15: 150000 | D15: 120000 | E15: 100000 | F15: Onboarding via koperasi/WhatsApp (low CAC).
B16: Payback period (bulan) | C16: =C15/C11 -> 8.3333333 | D16: =D15/D11 -> 2.6373626 | E16: =E15/E11 -> 0.95238095 | F16: =cac / kontribusi per bulan -> #VALUE!
B17: LTV / CAC (x) | C17: =C14/C15 -> 2.4 | D17: =D14/D15 -> 10.532407 | E17: =E14/E15 -> 37.5 | F17: =ltv / cac. >3 sehat. -> #VALUE!

Sheet Proyeksi
B2: PROYEKSI KEUANGAN 3 TAHUN (skenario Basis)
B4: Item | C4: Tahun 1 | D4: Tahun 2 | E4: Tahun 3
B5: UMKM aktif — awal tahun | C5: =100 -> 100 | D5: =C6 -> 1000 | E5: =D6 -> 10000
B6: UMKM aktif — akhir tahun | C6: 1000 | D6: 10000 | E6: 50000
B7: UMKM aktif — rata-rata | C7: =(C5+C6)/2 -> 550 | D7: =(D5+D6)/2 -> 5500 | E7: =(E5+E6)/2 -> 30000
B8: ARPU / bulan (Rp, Basis) | C8: =UnitEconomics!$D$9 -> 65000 | D8: =UnitEconomics!$D$9 -> 65000 | E8: =UnitEconomics!$D$9 -> 65000
B9: Pendapatan tahunan (Rp) | C9: =C7*C8*12 -> 429000000 | D9: =D7*D8*12 -> 4290000000 | E9: =E7*E8*12 -> 23400000000
B10: Biaya tetap tahunan (Rp) | C10: 600000000 | D10: 1500000000 | E10: 4000000000
B11: UMKM baru (akuisisi) | C11: =C6-C5 -> 900 | D11: =D6-D5 -> 9000 | E11: =E6-E5 -> 40000
B12: Biaya akuisisi (Rp) | C12: =C11*UnitEconomics!$D$15 -> 108000000 | D12: =D11*UnitEconomics!$D$15 -> 1080000000 | E12: =E11*UnitEconomics!$D$15 -> 4800000000
B13: Total biaya (Rp) | C13: =C10+C12 -> 708000000 | D13: =D10+D12 -> 2580000000 | E13: =E10+E12 -> 8800000000
B14: EBITDA (Rp) | C14: =C9-C13 -> -279000000 | D14: =D9-D13 -> 1710000000 | E14: =E9-E13 -> 14600000000
B15: Margin EBITDA | C15: =C14/C9 -> -0.65034965 | D15: =D14/D9 -> 0.3986014 | E15: =E14/E9 -> 0.62393162
B18: BREAK-EVEN OPERASIONAL (skenario Basis)
B19: Biaya tetap per bulan (Rp) — basis Tahun 2 | C19: =D10/12 -> 125000000
B20: Break-even = UMKM aktif dibutuhkan | C20: =C19/UnitEconomics!$D$11 -> 2747.2527
B21: (= biaya tetap bln / kontribusi per UMKM bln; belum termasuk amortisasi CAC)

Sheet TAM-SAM-SOM
B2: UKURAN PASAR (TAM / SAM / SOM)
B4: TAM — UMKM nasional | C4: 65500000 | D4: Sumber: OJK Institute 2025 / Kemenko Perekonomian
B5: SAM — % sektor target terjangkau digital | C5: 0.2 | D5: Kuliner/ritel/bahan pokok yang digital-reachable (asumsi konservatif)
B6: SAM — UMKM | C6: =C4*C5 -> 13100000 | D6: =tam × % -> #N/A
B7: SOM — target 3 tahun (UMKM aktif) | C7: 50000 | D7: Target Deschain 3 tahun
B8: Penetrasi SOM terhadap SAM | C8: =C7/C6 -> 0.0038167939 | D8: Sangat konservatif → ruang tumbuh besar
B9: ARPU tahunan (Rp, Basis) | C9: =UnitEconomics!D9*12 -> 780000 | D9: =arpu bln × 12 -> #N/A
B10: Potensi pendapatan SOM / tahun (Rp) | C10: =C7*C9 -> 39000000000 | D10: =som × ARPU tahunan -> #N/A
B11: Potensi pendapatan bila 5% SAM (Rp) | C11: =C6*0.05*C9 -> 510900000000 | D11: Skala menengah — ilustrasi ceiling

Sheet Asumsi-Sumber
B2: ASUMSI & SUMBER
B4: Semua angka adalah PROYEKSI berbasis asumsi, bukan realisasi.
B5: Sel KUNING = input yang bisa Anda ubah.
B7: Belanja stok warung mikro | D7: Rp7–21 juta/bulan (~70% omzet). kiosbank.id; ukmindonesia.id
B8: Take rate B2B Indonesia | D8: 1,5–2,0% (koridor ASEAN); global 0,1–3%. BCG 2023; a16z; asialifestylemagazine.com
B9: Adopsi lending sektor grocery | D9: ~3% (rendah) → monetisasi pembiayaan = jangka panjang. asialifestylemagazine.com
B10: Benchmark GPO/group buying | D10: Hemat rata-rata 13,1%; B2B 10–30%. bizequals.com; thrivebg.com
B11: Benchmark alt-credit (Konfio) | D11: 98,6% otomatis; gap SME $160B. reademergent.com; accion.org; IFC
B12: LTV/CAC sehat | D12: >3 (aturan umum SaaS/fintech).
B13: UMKM nasional / PDB / tenaga kerja | D13: 65,5 jt; 61,9% PDB; 97% kerja. OJK Institute 2025; ekon.go.id
B14: Kredit UMKM vs korporasi (Mar 2025) | D14: ~1,9% vs 13,52%, memburuk jadi kontraksi akhir 2025. Bank Indonesia; Kompas
B15: Regulasi pendukung | D15: POJK 29/2024 (ICS) & POJK 19/2025. ojk.go.id
